upbit/__init__.py
upbit/client.py
upbit/exceptions.py
python_upbit-0.1.1.dist-info/LICENSE
python_upbit-0.1.1.dist-info/METADATA
python_upbit-0.1.1.dist-info/WHEEL
python_upbit-0.1.1.dist-info/top_level.txt
python_upbit-0.1.1.dist-info/RECORD
