Metadata-Version: 2.1
Name: python-upbit
Version: 0.1.1
Summary: A python wrapper for UPBit
Home-page: https://github.com/time-percent/python-upbit
Author: Jungwoo Song
Author-email: timepercent24@gmail.com
License: MIT
Project-URL: Bug Reports, https://github.com/time-percent/python-upbit/issues
Project-URL: Source, https://github.com/time-percent/python-upbit/
Keywords: upbit,crypto,bitcoin
Platform: UNKNOWN
Classifier: Development Status :: 3 - Alpha
Classifier: Intended Audience :: Developers
Classifier: Topic :: Software Development :: Libraries :: Python Modules
Classifier: License :: OSI Approved :: MIT License
Classifier: Programming Language :: Python :: 3
Classifier: Programming Language :: Python :: 3.6
Classifier: Programming Language :: Python :: 3.7
Classifier: Programming Language :: Python :: 3.8
Requires-Python: >=3.6
Requires-Dist: requests
Requires-Dist: pyjwt
Requires-Dist: ratelimit
Requires-Dist: backoff
